clidup/__init__.py
clidup/__main__.py
clidup/cli/__init__.py
clidup/cli/main.py
clidup/config/__init__.py
clidup/config/loader.py
clidup/core/__init__.py
clidup/core/backup.py
clidup/core/compression.py
clidup/core/restore.py
clidup/databases/__init__.py
clidup/databases/base.py
clidup/databases/postgres.py
clidup/logging/__init__.py
clidup/logging/logger.py
clidup-0.2.4.dist-info/licenses/LICENSE
clidup-0.2.4.dist-info/METADATA
clidup-0.2.4.dist-info/WHEEL
clidup-0.2.4.dist-info/entry_points.txt
clidup-0.2.4.dist-info/top_level.txt
clidup-0.2.4.dist-info/RECORD
