Metadata-Version: 2.4
Name: clidup
Version: 0.2.4
Summary: Professional CLI tool for database backups and restores
Author-email: Geovani Pérez <geovaniperez0029@gmail.com>
Maintainer-email: Geovani Pérez <geovaniperez0029@gmail.com>
License: MIT
Project-URL: Homepage, https://github.com/Geovani29/clidup
Project-URL: Repository, https://github.com/Geovani29/clidup
Project-URL: Issues, https://github.com/Geovani29/clidup/issues
Project-URL: Documentation, https://github.com/Geovani29/clidup#readme
Keywords: database,backup,restore,postgresql,cli,pg_dump,database-backup,database-tools
Classifier: Development Status :: 4 - Beta
Classifier: Intended Audience :: Developers
Classifier: Intended Audience :: System Administrators
Classifier: Topic :: Database
Classifier: Topic :: System :: Archiving :: Backup
Classifier: Topic :: Utilities
Classifier: License :: OSI Approved :: MIT License
Classifier: Programming Language :: Python :: 3
Classifier: Programming Language :: Python :: 3.10
Classifier: Programming Language :: Python :: 3.11
Classifier: Programming Language :: Python :: 3.12
Classifier: Operating System :: OS Independent
Classifier: Environment :: Console
Requires-Python: >=3.10
License-File: LICENSE
Requires-Dist: typer>=0.9.0
Requires-Dist: rich>=10.11.0
Requires-Dist: pyyaml>=6.0
Requires-Dist: python-dotenv>=1.0.0
Provides-Extra: dev
Requires-Dist: build>=0.10.0; extra == "dev"
Requires-Dist: twine>=4.0.0; extra == "dev"
Dynamic: license-file
